mcp_ola_maps/__init__.py
mcp_ola_maps/main.py
mcp_ola_maps/mcp_env.py
mcp_ola_maps/mcp_server.py
mcp_ola_maps-0.1.3.dist-info/METADATA
mcp_ola_maps-0.1.3.dist-info/WHEEL
mcp_ola_maps-0.1.3.dist-info/entry_points.txt
mcp_ola_maps-0.1.3.dist-info/licenses/LICENSE
mcp_ola_maps-0.1.3.dist-info/RECORD
