Metadata-Version: 2.4
Name: mcp-ola-maps
Version: 0.1.3
Summary: MCP server for Ola Maps
License-Expression: MIT
License-File: LICENSE
Requires-Python: >=3.10
Requires-Dist: httpx>=0.28.1
Requires-Dist: mcp[cli]>=1.6.0
